LICENSE.txt
MANIFEST.in
setup.cfg
setup.py
svggraph/__init__.py
svggraph/hbarchartrenderer.py
svggraph/linegraphrender.py
svggraph/piechartrenderer.py
svggraph/util.py
svggraph.egg-info/PKG-INFO
svggraph.egg-info/SOURCES.txt
svggraph.egg-info/dependency_links.txt
svggraph.egg-info/requires.txt
svggraph.egg-info/top_level.txt