Metadata-Version: 1.1
Name: svggraph
Version: 0.0.5
Summary: SVG graph rendering library
Home-page: https://github.com/stevelittlefish/svggraph
Author: Stephen Brown (Little Fish Solutions LTD)
Author-email: opensource@littlefish.solutions
License: Apache
Download-URL: https://github.com/stevelittlefish/svggraph/archive/v0.0.5.tar.gz
Keywords: svg,graph,line,bar,pie
Platform: UNKNOWN
Classifier: License :: OSI Approved :: Apache Software License
Classifier: Development Status :: 5 - Production/Stable
Classifier: Intended Audience :: Developers
Classifier: Programming Language :: Python :: 3
Classifier: Topic :: Software Development :: Libraries
